caped_ai_tabulour/__init__.py
caped_ai_tabulour/_data_model.py
caped_ai_tabulour/_tabulour.py
caped_ai_tabulour/_version.py
caped_ai_tabulour/caped.yaml
caped_ai_tabulour/_tests/__init__.py
caped_ai_tabulour/_tests/test_tabulour.py
caped_ai_tabulour-0.1.4.dist-info/LICENSE
caped_ai_tabulour-0.1.4.dist-info/METADATA
caped_ai_tabulour-0.1.4.dist-info/WHEEL
caped_ai_tabulour-0.1.4.dist-info/entry_points.txt
caped_ai_tabulour-0.1.4.dist-info/top_level.txt
caped_ai_tabulour-0.1.4.dist-info/RECORD
