Metadata-Version: 2.1
Name: caped-ai-tabulour
Version: 0.1.4
Summary: A base table widget for KapoorLabs Napari plugins
Home-page: https://github.com/Kapoorlabs-CAPED/caped-ai-tabulour
Author: Varun Kapoor
Author-email: randomaccessiblekapoor@gmail.com
License: BSD-3-Clause
Project-URL: Bug Tracker, https://github.com/Kapoorlabs-CAPED/caped-ai-tabulour/issues
Project-URL: Documentation, https://github.com/Kapoorlabs-CAPED/caped-ai-tabulour#README.md
Project-URL: Source Code, https://github.com/Kapoorlabs-CAPED/caped-ai-tabulour
Project-URL: User Support, https://github.com/Kapoorlabs-CAPED/caped-ai-tabulour/issues
Classifier: Development Status :: 5 - Production/Stable
Classifier: Intended Audience :: Developers
Classifier: License :: OSI Approved :: BSD License
Classifier: Operating System :: OS Independent
Classifier: Programming Language :: Python
Classifier: Programming Language :: Python :: 3
Classifier: Programming Language :: Python :: 3 :: Only
Classifier: Programming Language :: Python :: 3.8
Classifier: Programming Language :: Python :: 3.9
Classifier: Programming Language :: Python :: 3.10
Classifier: Topic :: Scientific/Engineering :: Image Processing
Requires-Python: >=3.8
License-File: LICENSE
Requires-Dist: napari
Requires-Dist: pandas
Requires-Dist: numpy
Provides-Extra: testing
Requires-Dist: tox ; extra == 'testing'
Requires-Dist: pytest ; extra == 'testing'
Requires-Dist: pytest-cov ; extra == 'testing'
